setup.py
splunk_http_handler/__init__.py
splunk_http_handler.egg-info/PKG-INFO
splunk_http_handler.egg-info/SOURCES.txt
splunk_http_handler.egg-info/dependency_links.txt
splunk_http_handler.egg-info/requires.txt
splunk_http_handler.egg-info/top_level.txt