Metadata-Version: 1.1
Name: splunk-http-handler
Version: 1.0.0
Summary: A Python logging handler that sends your logs to Splunk over HTTP event collector
Home-page: https://github.com/vlad-shevtsov-mev/splunk_http_handler
Author: MEV, LLC
Author-email: vlad.shevtsov@mev.com
License: MIT License
Platform: UNKNOWN
Classifier: Development Status :: 4 - Beta
Classifier: Intended Audience :: Developers
Classifier: License :: OSI Approved :: MIT License
Classifier: Natural Language :: English
Classifier: Operating System :: POSIX :: Linux
Classifier: Operating System :: MacOS :: MacOS X
Classifier: Programming Language :: Python
Classifier: Programming Language :: Python :: 2.7
Classifier: Programming Language :: Python :: 3.4
Classifier: Programming Language :: Python :: 3.5
Classifier: Programming Language :: Python :: 3.6
Classifier: Topic :: System :: Logging
